{
  "GOBLIN": {
    "name": "Goblin Scout",
    "hp": 20,
    "pattern":[
        {"card":"STRIKE", "target":"player", "time": 1},
        {"card":"STRIKE", "target":"player", "time": 1},
        {"card":"PATCH_UP", "target":"self", "time": 1}
    ],
    "image": "./Enemy/Goblin.png"
  },
   "SPEAR_GOBLIN": {
    "name": "Goblin Spear Thrower",
    "hp": 15,
    "pattern":[
        {"card":"CHARGE", "target":"self", "time": 0},
        {"card":"DOUBLE_STRIKE", "target":"player", "time": 1},
        {"card":"STRIKE", "target":"player", "time": 1},
        {"card":"STRIKE", "target":"player", "time": 1}
    ],
    "image": "./Enemy/Spear_Goblin.png"
  },
   "STRONG_GOBLIN": {
    "name": "Strong Goblin",
    "hp": 80,
    "pattern":[
        {"card":"STRIKE", "target":"player", "time": 1},
        {"card":"HEAVY_STRIKE", "target":"player", "time": 1},
        {"card":"PATCH_UP", "target":"self", "time": 0}
    ],
    "image": "./Enemy/Strong_Goblin.png"
  },
   "GOBLIN_SOLDIER": {
    "name": "Goblin Soldier",
    "hp": 35,
    "pattern":[
        {"card":"DEFEND", "target":"self", "time": 0},
        {"card":"STRIKE", "target":"player", "time": 1},
        {"card":"DOUBLE_STRIKE", "target":"player", "time": 1}
    ],
    "image": "./Enemy/Goblin_Soldier.png"
  },
  "SKELETON":{
    "name": "Skeleton",
    "hp": 3,
    "pattern":[
        {"card":"STRIKE", "target":"player", "time": 1}
    ],
    "image": "./Enemy/Skeleton.png"
  },
    "SKELETON_SOLDIER":{
    "name": "Skeleton Soldier",
    "hp": 10,
    "pattern":[
        {"card":"DEFEND", "target":"self", "time": 0},
        {"card":"DOUBLE_STRIKE", "target":"player", "time": 1},
        {"card":"DOUBLE_STRIKE", "target":"player", "time": 1}
    ],
    "image": "./Enemy/Skeleton_Soldier.png"
  },
    "ELITE_SKELETON":{
    "name": "Elite Skeleton Soldier",
    "hp": 15,
    "pattern":[
        {"card":"GUARD", "target":"self", "time": 1},
        {"card":"CHARGE", "target":"self", "time": 1},
        {"card":"DOUBLE_STRIKE", "target":"player", "time": 0},
        {"card":"STRIKE", "target":"player", "time": 1}

    ],
    "image": "./Enemy/Elite_Skeleton.png"
  },
  "VAMPIRE_BAT": {
    "name": "Vampire Bat",
    "hp": 30,
    "pattern":[
        {"card":"VAMPIRE", "target":"player", "time": 1},
        {"card":"VAMPIRE", "target":"player", "time": 1},
        {"card":"VAMPIRE", "target":"player", "time": 1}
    ],
    "image": "./Enemy/Bat.png"
  },
  "SLIME": {
    "name": "Slime",
    "hp": 20,
    "pattern":[
        {"card":"REGENERATION", "target":"self", "time": 1},
        {"card":"STRIKE", "target":"player", "time": 1},
        {"card":"STRIKE", "target":"player", "time": 1}
    ],
    "image": "./Enemy/Slime.png"
  },
  "STONE_GOLEM": {
    "name": "Stone Golem",
    "hp": 30,
    "pattern":[
        {"card":"FORTIFY", "target":"self", "time": 1},
        {"card":"GUARD", "target":"self", "time": 1},
        {"card":"HEAVY_STRIKE", "target":"player", "time": 2},
        {"card":"DEFEND", "target":"self", "time": 1}
    ],
    "image": "./Enemy/Stone_Golem.png"
  },
   "GIANT_SPIDER": {
    "name": "Giant Spider",
    "hp": 10,
    "pattern":[
        {"card":"DOUBLE_STRIKE", "target":"player", "time": 1},
        {"card":"FIVEFOLD_STRIKE", "target":"player", "time": 1}

    ],
    "image": "./Enemy/Giant_Spider.png"
  },
  "OLD_DRAGON": {
    "name": "The Old Dragon",
    "hp": 100,
    "pattern_type": "Random",
    "pattern":[
        [ {"card":"KINDLE", "target":"player"}, {"card":"FIREBALL", "target":"player"} ],
        [ {"card":"GUARD", "target":"self"}, {"card":"PATCH_UP", "target":"self"}, {"card":"PATCH_UP", "target":"self"} ],
        [ {"card":"QUICK_STRIKE", "target":"player"}, {"card":"QUICK_STRIKE", "target":"player"} ],
        [ {"card":"REST", "target":"self"} ],
        [ {"card":"PYRO_PUNCH", "target":"player"}, {"card":"PYRO_PUNCH", "target":"player"} ]
    ],
    "image": "./Enemy/Old_Dragon.png"
  },
  "RED_DRAGON": {
    "name": "The Red Dragon",
    "hp": 200,
    "pattern_type": "Random",
    "pattern":[
        [ {"card":"KINDLE", "target":"player"}, {"card":"FIREBALL", "target":"player"} ,{"card":"FIREBALL", "target":"player"} ],
        [ {"card":"GUARD", "target":"self"}, {"card":"REGENERATION", "target":"self"}, {"card":"REGENERATION", "target":"self"} ],
        [ {"card":"STRIKE", "target":"player"}, {"card":"DOUBLE_STRIKE", "target":"player"} ],
        [ {"card":"REST", "target":"self"} ],
        [ {"card":"BLAZING_FLURRY", "target":"player"}, {"card":"PYRO_PUNCH", "target":"player"} ]
    ],
    "image": "./Enemy/Red_Dragon.png"
  }
}